fastsolv/__init__.py
fastsolv/_classes.py
fastsolv/_cli.py
fastsolv/_module.py
fastsolv-1.0.1.dist-info/METADATA
fastsolv-1.0.1.dist-info/WHEEL
fastsolv-1.0.1.dist-info/entry_points.txt
fastsolv-1.0.1.dist-info/top_level.txt
fastsolv-1.0.1.dist-info/RECORD
