Metadata-Version: 2.4
Name: fastsolv
Version: 1.0.1
Summary: fastsolv solid solubility predictor
Author: Jackson Burns
License: MIT
Project-URL: Homepage, https://github.com/JacksonBurns/fastsolv
Classifier: Programming Language :: Python :: 3
Requires-Python: >=3.8
Requires-Dist: fastprop
Requires-Dist: torch
Requires-Dist: pandas
Requires-Dist: numpy
